{"_format":"","paths":{"artifacts":"out","build_infos":"out/build-info","sources":"contracts","tests":"test","scripts":"script","libraries":["lib"]},"files":{"contracts/VedhStateAnchor.sol":{"lastModificationDate":1769825571087,"contentHash":"7b9b462c536abc996fdce20ac0c851a4","sourceName":"contracts/VedhStateAnchor.sol","imports":[],"versionRequirement":"^0.8.20","artifacts":{"VedhStateAnchor":{"0.8.20":{"default":{"path":"VedhStateAnchor.sol/VedhStateAnchor.json","build_id":"c9ca01d026e270ce74d6fd630fff0a33"}}}},"seenByCompiler":true},"test/VedhStateAnchor.t.sol":{"lastModificationDate":1769829808001,"contentHash":"9218e117bfc3ea107dd489d233d611c3","sourceName":"test/VedhStateAnchor.t.sol","imports":["contracts/VedhStateAnchor.sol"],"versionRequirement":"^0.8.20","artifacts":{"VedhStateAnchorTest":{"0.8.20":{"default":{"path":"VedhStateAnchor.t.sol/VedhStateAnchorTest.json","build_id":"998a9eecdd520da9aedfc033fefb73df"}}},"Vm":{"0.8.20":{"default":{"path":"VedhStateAnchor.t.sol/Vm.json","build_id":"998a9eecdd520da9aedfc033fefb73df"}}}},"seenByCompiler":true}},"builds":["998a9eecdd520da9aedfc033fefb73df","c9ca01d026e270ce74d6fd630fff0a33"],"profiles":{"default":{"solc":{"optimizer":{"enabled":true,"runs":200},"metadata":{"useLiteralContent":false,"bytecodeHash":"ipfs","appendCBOR":true},"outputSelection":{"*":{"*":["abi","evm.bytecode.object","evm.bytecode.sourceMap","evm.bytecode.linkReferences","evm.deployedBytecode.object","evm.deployedBytecode.sourceMap","evm.deployedBytecode.linkReferences","evm.deployedBytecode.immutableReferences","evm.methodIdentifiers","metadata"]}},"evmVersion":"shanghai","viaIR":true,"libraries":{}},"vyper":{"evmVersion":"shanghai","outputSelection":{"*":{"*":["abi","evm.bytecode","evm.deployedBytecode"]}}}}}}